target_snowflake/__init__.py
target_snowflake/connector.py
target_snowflake/initializer.py
target_snowflake/sinks.py
target_snowflake/snowflake_types.py
target_snowflake/target.py
meltanolabs_target_snowflake-0.18.6.dist-info/METADATA
meltanolabs_target_snowflake-0.18.6.dist-info/WHEEL
meltanolabs_target_snowflake-0.18.6.dist-info/entry_points.txt
meltanolabs_target_snowflake-0.18.6.dist-info/licenses/LICENSE
meltanolabs_target_snowflake-0.18.6.dist-info/RECORD
